ak_filenames.py
fzj_ak_filenames-2.1.dist-info/LICENSE
fzj_ak_filenames-2.1.dist-info/METADATA
fzj_ak_filenames-2.1.dist-info/WHEEL
fzj_ak_filenames-2.1.dist-info/top_level.txt
fzj_ak_filenames-2.1.dist-info/RECORD
