Metadata-Version: 2.1
Name: fzj-ak-filenames
Version: 2.1
Summary: Filename parser & writer for fusion device configuration-related files
Home-page: https://github.com/alexrobomind/ak_filenames
Author: Alexander Knieps
Author-email: a.knieps@fz-juelich.de
License: UNKNOWN
Platform: UNKNOWN
Requires-Dist: textX (>=2.1.0)
